mongo_migrations/__init__.py
mongo_migrations/commands.py
mongo_migrations/migrations.py
mongo_migrations-0.3.0.dist-info/METADATA
mongo_migrations-0.3.0.dist-info/RECORD
mongo_migrations-0.3.0.dist-info/WHEEL
mongo_migrations-0.3.0.dist-info/entry_points.txt
mongo_migrations-0.3.0.dist-info/top_level.txt
