Metadata-Version: 2.1
Name: mongo-migrations
Version: 0.3.0
Summary: Provides possibility to create and manage migrations for MongoDB
Home-page: https://bitbucket.org/submax82/mongo_migrations
Author: Massimo Cavalleri
Author-email: submax@tiscali.it
License: BSD
Platform: any
Classifier: Environment :: Web Environment
Classifier: Intended Audience :: Developers
Classifier: License :: OSI Approved :: BSD License
Classifier: Operating System :: OS Independent
Classifier: Programming Language :: Python
Classifier: Topic :: Internet :: WWW/HTTP :: Dynamic Content
Classifier: Topic :: Software Development :: Libraries :: Python Modules
Requires-Dist: pymongo
Requires-Dist: click
